malaysia_prayer_time/__init__.py
malaysia_prayer_time/__main__.py
malaysia_prayer_time/main.py
mseep_malaysia_prayer_time-0.2.3.dist-info/licenses/LICENSE
mseep_malaysia_prayer_time-0.2.3.dist-info/METADATA
mseep_malaysia_prayer_time-0.2.3.dist-info/WHEEL
mseep_malaysia_prayer_time-0.2.3.dist-info/entry_points.txt
mseep_malaysia_prayer_time-0.2.3.dist-info/top_level.txt
mseep_malaysia_prayer_time-0.2.3.dist-info/RECORD
