Metadata-Version: 2.4
Name: mseep-malaysia-prayer-time
Version: 0.2.3
Summary: Malaysia Prayer Time MCP Server for Claude Desktop
Author-email: mseep <support@skydeck.ai>
Project-URL: Homepage, https://github.com/yourusername/mcp-server-malaysia-prayer-time
Project-URL: Bug Tracker, https://github.com/yourusername/mcp-server-malaysia-prayer-time/issues
Classifier: Programming Language :: Python :: 3
Classifier: License :: OSI Approved :: MIT License
Classifier: Operating System :: OS Independent
Requires-Python: >=3.10
License-File: LICENSE
Requires-Dist: httpx>=0.27.0
Requires-Dist: pydantic<3.0.0,>=2.0.0
Requires-Dist: PyYAML<7.0,>=6.0
Requires-Dist: mcp>=1.2.0
Requires-Dist: mcp[cli]>=1.2.0
Dynamic: license-file
